nbplantuml/__init__.py
nbplantuml-0.1.0.dist-info/DESCRIPTION.rst
nbplantuml-0.1.0.dist-info/METADATA
nbplantuml-0.1.0.dist-info/RECORD
nbplantuml-0.1.0.dist-info/WHEEL
nbplantuml-0.1.0.dist-info/metadata.json
nbplantuml-0.1.0.dist-info/top_level.txt
