Metadata-Version: 2.0
Name: nbplantuml
Version: 0.1.0
Summary: Easily embed plantuml diagrams in your IPython noteboooks
Home-page: UNKNOWN
Author: Eyal Firstenberg
Author-email: eyalfir@gmail.com
License: UNKNOWN
Platform: UNKNOWN
Classifier: Development Status :: 4 - Beta
Requires-Dist: ipython
Requires-Dist: plantuml
